.hgignore
.hgtags
HISTORY.rst
README.rst
TODO.txt
mercurial_update_version.py
noxfile.py
setup.py
mercurial_update_version.egg-info/PKG-INFO
mercurial_update_version.egg-info/SOURCES.txt
mercurial_update_version.egg-info/dependency_links.txt
mercurial_update_version.egg-info/requires.txt
mercurial_update_version.egg-info/top_level.txt
mercurial_update_version.egg-info/zip-safe
tests/dirty.t
tests/file-selection.t
tests/tag-by-version.t
tests/tag-cvs-and-cxx.t
tests/tag-cvs.t
tests/tag-multiple-languages-and-keywords.t
tests/tag-multiple-languages.t
tests/tag-reactions.t
tests/tag-singlerepo-multiple-languages.t
tests/tag-singlerepo.t
tests/test_version_parsing.py
tests/various-languages-01.t
tests/various-languages-02.t
tests/various-languages-03.t